{
    "best_solution_capacities": {
        "Port authority of New York and New Jersey, NY & NJ": 165720,
        "Port of los angeles, CA": 155453,
        "Port of long beach, CA": 138722,
        "Port of savannah, GA": 91592,
        "Port of houston authority of harris county, TX": 60474,
        "Port of virginia, VA": 63521,
        "Port of charleston, SC": 43100,
        "Port of oakland, CA": 29810,
        "Port of seattle, WA": 20396,
        "Tacoma, WA": 19862,
        "Port miami, FL": 16786,
        "Philadelphia regional port authority, PA": 18854,
        "Baltimore, MD": 19717,
        "Port everglades, FL": 14918,
        "Mobile, AL": 11229,
        "San juan, PR": 8205,
        "Jacksonville, FL": 8148,
        "Wilmington, DE": 7259,
        "Oxnard harbor district, CA": 5269,
        "Port of new orleans, LA": 4931,
        "Wilmington, NC": 4677,
        "Port of gulfport, MS": 3597,
        "South jersey port corporation, NJ": 2599
    },
    "dummy_detector_accuracies": [
        0.868,
        0.82,
        0.788,
        0.67,
        0.8,
        0.4,
        0.4,
        0.5,
        0.5,
        0,
        0,
        0,
        0,
        0,
        0,
        0,
        0,
        0,
        0,
        0,
        0,
        0,
        0
    ],
    "expected_fraction_detected_each_year": {
        "2017": 0.31219936657100894,
        "2018": 0.5601070827097603,
        "2019": 0.6536527148408537,
        "2020": 0.3304768871413497,
        "2021": 0.7168468452644462,
        "2022": 0.7891999999999999
    }
}